blackjack_gui/__init__.py
blackjack_gui/blackjack.py
blackjack_gui/cli.py
blackjack_gui/gui.py
blackjack_gui/lib.py
blackjack_gui/settings.py
blackjack_gui/table_components.py
blackjack_gui/version.py
blackjack_gui/images/10_of_clubs.png
blackjack_gui/images/10_of_diamonds.png
blackjack_gui/images/10_of_hearts.png
blackjack_gui/images/10_of_spades.png
blackjack_gui/images/2_of_clubs.png
blackjack_gui/images/2_of_diamonds.png
blackjack_gui/images/2_of_hearts.png
blackjack_gui/images/2_of_spades.png
blackjack_gui/images/3_of_clubs.png
blackjack_gui/images/3_of_diamonds.png
blackjack_gui/images/3_of_hearts.png
blackjack_gui/images/3_of_spades.png
blackjack_gui/images/4_of_clubs.png
blackjack_gui/images/4_of_diamonds.png
blackjack_gui/images/4_of_hearts.png
blackjack_gui/images/4_of_spades.png
blackjack_gui/images/5_of_clubs.png
blackjack_gui/images/5_of_diamonds.png
blackjack_gui/images/5_of_hearts.png
blackjack_gui/images/5_of_spades.png
blackjack_gui/images/6_of_clubs.png
blackjack_gui/images/6_of_diamonds.png
blackjack_gui/images/6_of_hearts.png
blackjack_gui/images/6_of_spades.png
blackjack_gui/images/7_of_clubs.png
blackjack_gui/images/7_of_diamonds.png
blackjack_gui/images/7_of_hearts.png
blackjack_gui/images/7_of_spades.png
blackjack_gui/images/8_of_clubs.png
blackjack_gui/images/8_of_diamonds.png
blackjack_gui/images/8_of_hearts.png
blackjack_gui/images/8_of_spades.png
blackjack_gui/images/9_of_clubs.png
blackjack_gui/images/9_of_diamonds.png
blackjack_gui/images/9_of_hearts.png
blackjack_gui/images/9_of_spades.png
blackjack_gui/images/ace_of_clubs.png
blackjack_gui/images/ace_of_diamonds.png
blackjack_gui/images/ace_of_hearts.png
blackjack_gui/images/ace_of_spades.png
blackjack_gui/images/ace_of_spades2.png
blackjack_gui/images/back.png
blackjack_gui/images/bj-shot.png
blackjack_gui/images/black_joker.png
blackjack_gui/images/blue-chip.png
blackjack_gui/images/chart-helsinki.png
blackjack_gui/images/chart-symbols.png
blackjack_gui/images/chart-usa.png
blackjack_gui-1.8.1.dist-info/LICENSE
blackjack_gui-1.8.1.dist-info/METADATA
blackjack_gui-1.8.1.dist-info/WHEEL
blackjack_gui-1.8.1.dist-info/entry_points.txt
blackjack_gui-1.8.1.dist-info/top_level.txt
blackjack_gui-1.8.1.dist-info/RECORD
