Metadata-Version: 2.2
Name: blackjack-gui
Version: 1.8.1
Summary: A game of Blackjack with graphical user interface.
Author-email: Simo Tukiainen <tukiains@gmail.com>
License: MIT License
Project-URL: Homepage, https://github.com/tukiains/blackjack-gui
Project-URL: Documentation, https://github.com/tukiains/blackjack-gui
Project-URL: Repository, https://github.com/tukiains/blackjack-gui
Project-URL: Changelog, https://github.com/tukiains/blackjack-gui/CHANGELOG.md
Classifier: Development Status :: 5 - Production/Stable
Classifier: License :: OSI Approved :: MIT License
Classifier: Operating System :: OS Independent
Classifier: Programming Language :: Python :: 3.10
Classifier: Programming Language :: Python :: 3.11
Classifier: Programming Language :: Python :: 3.12
Classifier: Topic :: Games/Entertainment
Requires-Python: >=3.10
License-File: LICENSE
Requires-Dist: pillow
Provides-Extra: test
Requires-Dist: mypy; extra == "test"
Requires-Dist: pytest; extra == "test"
Requires-Dist: pytest-flakefinder; extra == "test"
Requires-Dist: ruff; extra == "test"
Requires-Dist: types-Pillow; extra == "test"
Provides-Extra: dev
Requires-Dist: pre-commit; extra == "dev"
Requires-Dist: release-version; extra == "dev"
